[
    {
        "title": "褍胁褍胁褍",
        "text": "褑褑褑褑",
        "file": "uploads\/1776769907_Frame3.png",
        "type": "image",
        "date": "21.04.2026"
    },
    {
        "title": "锌褉芯谢写芯芯芯芯芯芯芯芯",
        "text": "芯芯芯芯芯芯芯芯芯芯芯芯芯芯芯芯芯芯芯芯芯芯芯芯芯芯芯芯芯芯芯芯芯芯芯芯芯芯芯芯芯芯芯芯芯芯芯芯芯芯芯芯芯芯芯芯芯芯芯芯芯芯芯芯芯芯芯芯芯芯芯芯芯芯芯芯芯芯芯芯芯芯芯芯芯芯芯芯芯芯芯芯芯芯芯芯芯芯芯芯芯芯芯芯芯芯芯芯芯芯芯芯芯芯芯芯芯芯芯芯芯芯芯芯芯芯芯芯芯芯芯芯芯芯芯芯芯芯芯芯芯芯芯芯芯芯芯芯芯芯芯芯芯芯芯芯芯芯芯芯芯芯芯芯芯芯芯芯芯芯芯芯芯芯芯芯芯芯芯芯芯芯芯芯芯",
        "date": "24.04.2026"
    },
    {
        "title": "234械薪谐",
        "text": "2134械薪谐械泻4褑械泻褍薪泻械",
        "date": "24.04.2026"
    }
]